robotframework_i2c/__init__.py
robotframework_i2c/I2CLibrary/I2CLibrary.py
robotframework_i2c/I2CLibrary/__init__.py
robotframework_i2c/examples/__init__.py
robotframework_i2c/examples/i2c_demo.robot
robotframework_i2c/examples/i2c_test.robot
robotframework_i2c-1.0.0.dist-info/licenses/LICENSE
robotframework_i2c-1.0.0.dist-info/METADATA
robotframework_i2c-1.0.0.dist-info/WHEEL
robotframework_i2c-1.0.0.dist-info/top_level.txt
robotframework_i2c-1.0.0.dist-info/RECORD
