Metadata-Version: 2.4
Name: robotframework-i2c
Version: 1.0.0
Summary: Robot Framework Library for interfacing I2C devices on Raspberry Pi and other embedded systems
Author-email: RZ-CI Team <rz-ci@renesas.com>
License-Expression: MIT
Project-URL: Homepage, https://github.com/renesas/robotframework-i2c
Project-URL: Documentation, https://renesas.github.io/robotframework-i2c/
Project-URL: Repository, https://github.com/renesas/robotframework-i2c
Project-URL: Issues, https://github.com/renesas/robotframework-i2c/issues
Keywords: robot,framework,i2c,raspberry,pi,embedded,hardware,automation
Classifier: Development Status :: 4 - Beta
Classifier: Intended Audience :: Developers
Classifier: Programming Language :: Python :: 3
Classifier: Programming Language :: Python :: 3.8
Classifier: Programming Language :: Python :: 3.9
Classifier: Programming Language :: Python :: 3.10
Classifier: Programming Language :: Python :: 3.11
Classifier: Topic :: Software Development :: Testing
Classifier: Topic :: System :: Hardware
Classifier: Framework :: Robot Framework
Classifier: Framework :: Robot Framework :: Library
Requires-Python: >=3.8
License-File: LICENSE
Requires-Dist: robotframework>=3.2.2
Requires-Dist: smbus2>=0.4.0
Provides-Extra: dev
Requires-Dist: pytest>=6.0; extra == "dev"
Requires-Dist: black>=21.0.0; extra == "dev"
Requires-Dist: flake8>=3.8.0; extra == "dev"
Provides-Extra: docs
Requires-Dist: sphinx>=4.0.0; extra == "docs"
Requires-Dist: sphinx-rtd-theme>=1.2.0; extra == "docs"
Dynamic: license-file
